rp_backscatter/__init__.py
rp_backscatter/backscatter_packaged.py
rp_backscatter/post_pip_backscatter_test.py
rp_backscatter/rp_initialization.py
rp_backscatter/ssh_connection.py
rp_backscatter-0.1.2.dist-info/METADATA
rp_backscatter-0.1.2.dist-info/WHEEL
rp_backscatter-0.1.2.dist-info/licenses/LICENSE
rp_backscatter-0.1.2.dist-info/RECORD
