Metadata-Version: 2.4
Name: rp_backscatter
Version: 0.1.2
Summary: Usage of Red Pitaya embedded signal acquisition platform to collect backscatter data from INSITE2 chip
Project-URL: Homepage, https://github.com/anwar-lab-ucb/rp_backscatter
Project-URL: Issues, https://github.com/anwar-lab-ucb/rp_backscatter
Author-email: Kingshuk Daschowdhury <kingshukd@berkeley.edu>
License-File: LICENSE
Classifier: License :: OSI Approved :: GNU General Public License v3 (GPLv3)
Classifier: Operating System :: OS Independent
Classifier: Programming Language :: Python :: 3
Requires-Python: >=3.0
